{
  "hand_number": 3,
  "num_players": 2,
  "button": 0,
  "board": [
    null,
    null,
    null,
    null,
    null
  ],
  "players": [
    {
      "index": 0,
      "name": "You",
      "hole_cards": [
        23,
        3
      ],
      "starting_chips": 400,
      "difficulty": "human"
    },
    {
      "index": 1,
      "name": "AI 1",
      "hole_cards": [
        30,
        22
      ],
      "starting_chips": 400,
      "difficulty": "advanced"
    }
  ],
  "action_log": [
    {
      "type": "street",
      "street": "PREFLOP",
      "board": []
    },
    {
      "player": 0,
      "name": "You",
      "action": "fold",
      "amount": 0,
      "street": "WAITING",
      "timestamp": 1773842921.190114
    }
  ],
  "debug_events": [
    {
      "type": "hand_start",
      "hand_number": 3,
      "button": 1,
      "players": [
        {
          "index": 0,
          "name": "You",
          "chips": 400,
          "hole_cards": [
            23,
            3
          ],
          "difficulty": "human"
        },
        {
          "index": 1,
          "name": "AI 1",
          "chips": 397,
          "hole_cards": [
            30,
            22
          ],
          "difficulty": "advanced"
        }
      ],
      "timestamp": 1773842918.6236238
    }
  ]
}